pdf2cb/__init__.py
pdf2cb/__main__.py
pdf2cb/app.py
pdf2cb/cli.py
pdf_to_cb-1.0.0.dist-info/METADATA
pdf_to_cb-1.0.0.dist-info/WHEEL
pdf_to_cb-1.0.0.dist-info/entry_points.txt
pdf_to_cb-1.0.0.dist-info/RECORD
