Metadata-Version: 2.1
Name: pdf-to-cb
Version: 1.0.0
Summary: PDF to Comic Book format
License: Apache-2.0
Author: Marco Ceppi
Author-email: marco@ceppi.net
Requires-Python: >=3.11,<4.0
Classifier: License :: OSI Approved :: Apache Software License
Classifier: Programming Language :: Python :: 3
Classifier: Programming Language :: Python :: 3.11
Classifier: Programming Language :: Python :: 3.12
Requires-Dist: pdf2image (>=1.17.0,<2.0.0)
Requires-Dist: rich (>=13.7.0,<14.0.0)
Requires-Dist: typer (>=0.9.0,<0.10.0)
